TrafficSignalControl.v
`timescale 1ns / 1ps

// Define constants
`define TRUE  1'b1
`define FALSE 1'b0
`define RED   2'd0
`define YELLOW 2'd1
`define GREEN 2'd2

// State definition
`define S0 3'd0  // GREEN
`define S1 3'd1  // YELLOW
`define S2 3'd2  // RED
`define S3 3'd3  // RED (for HWY)
`define S4 3'd4  // RED (for CNTRY)

// Delays
`define Y2RDELAY 3 // Yellow to red delay
`define R2GDELAY 2 // Red to green delay

module sig_control (
    output reg [1:0] hwy, cntry, // 2-bit outputs for the states of signals
    input wire X,                // If TRUE, indicates that there is a car on the country road, otherwise FALSE
    input wire clock, clear      // Clock and clear inputs
);

// Internal state variables
reg [2:0] state, next_state;
reg [3:0] counter; // Counter for delays

// Signal controller starts in S0 state
initial begin
    state = `S0;
    next_state = `S0;
    hwy = `GREEN;
    cntry = `RED;
    counter = 0;
end

// State changes only at the positive edge of the clock
always @(posedge clock) begin
    if (clear) begin
        state <= `S0;
        counter <= 0;
    end else begin
        state <= next_state;
        if (counter > 0) counter <= counter - 1;
    end
end

// Compute values of main signal (hwy) and country signal (cntry)
always @(state) begin
    case (state)
        `S0: begin
            hwy = `GREEN;
            cntry = `RED;
            counter = `Y2RDELAY;
        end
        `S1: begin
            hwy = `YELLOW;
            cntry = `RED;
            counter = `Y2RDELAY;
        end
        `S2: begin
            hwy = `RED;
            cntry = `RED;
            counter = `R2GDELAY;
        end
        `S3: begin
            hwy = `RED;
            cntry = `GREEN;
            counter = 0; // No delay
        end
        `S4: begin
            hwy = `RED;
            cntry = `YELLOW;
            counter = `Y2RDELAY;
        end
        default: begin
            hwy = `RED;
            cntry = `RED;
            counter = 0;
        end
    endcase
end

// State machine using case statements
always @(posedge clock) begin
    if (clear) 
        next_state <= `S0;
    else if (counter == 0) begin
        case (state)
            `S0: next_state <= (X ? `S1 : `S0);
            `S1: next_state <= `S2;
            `S2: next_state <= `S3;
            `S3: next_state <= (X ? `S3 : `S4);
            `S4: next_state <= `S0;
            default: next_state <= `S0;
        endcase
    end
end

endmodule

TrafficTestBench.v
`timescale 1ns / 1ps
`include "TrafficSignalControl.v"
// Define constants
`define TRUE  1'b1
`define FALSE 1'b0

module stimulus;
    wire [1:0] MAIN_SIG, CNTRY_SIG;
    reg CAR_ON_CNTRY_RD;
    reg CLOCK, CLEAR;

    // Dump signals to a VCD file
    initial begin
        $dumpfile("traffic_light_controller.vcd");
        $dumpvars(0, stimulus);
    end

    // Instantiate the sig_control module
    sig_control SC (
        .hwy(MAIN_SIG),
        .cntry(CNTRY_SIG),
        .X(CAR_ON_CNTRY_RD),
        .clock(CLOCK),
        .clear(CLEAR)
    );

    // Set up monitor
    initial begin
        $monitor($time, " Main Sig = %b, Country Sig = %b, Car_on_cntry = %b", MAIN_SIG, CNTRY_SIG, CAR_ON_CNTRY_RD);
    end

    // Set up clock
    initial begin
        CLOCK = `FALSE;
        forever #5 CLOCK = ~CLOCK; // Clock period of 10ns
    end

    // Control clear signal
    initial begin
        CLEAR = `TRUE;
        repeat (5) @ (negedge CLOCK);
        CLEAR = `FALSE;
    end

    // Apply stimulus
    initial begin
        CAR_ON_CNTRY_RD = `FALSE;
        #200 CAR_ON_CNTRY_RD = `TRUE;
        #100 CAR_ON_CNTRY_RD = `FALSE;
        #200 CAR_ON_CNTRY_RD = `TRUE;
        #100 CAR_ON_CNTRY_RD = `FALSE;
        #200 CAR_ON_CNTRY_RD = `TRUE;
        #100 CAR_ON_CNTRY_RD = `FALSE;
        #100 $stop;
    end
endmodule

traffic_light_controller.vcd
$date
	Wed Aug 21 16:44:32 2024
$end
$version
	Icarus Verilog
$end
$timescale
	1ps
$end
$scope module stimulus $end
$var wire 2 ! MAIN_SIG [1:0] $end
$var wire 2 " CNTRY_SIG [1:0] $end
$var reg 1 # CAR_ON_CNTRY_RD $end
$var reg 1 $ CLEAR $end
$var reg 1 % CLOCK $end
$scope module SC $end
$var wire 1 # X $end
$var wire 1 $ clear $end
$var wire 1 % clock $end
$var reg 2 & cntry [1:0] $end
$var reg 4 ' counter [3:0] $end
$var reg 2 ( hwy [1:0] $end
$var reg 3 ) next_state [2:0] $end
$var reg 3 * state [2:0] $end
$upscope $end
$upscope $end
$enddefinitions $end
$comment Show the parameter values. $end
$dumpall
$end
#0
$dumpvars
b0 *
b0 )
b10 (
b11 '
b0 &
0%
1$
0#
b0 "
b10 !
$end
#5000
b0 '
1%
#10000
0%
#15000
1%
#20000
0%
#25000
1%
#30000
0%
#35000
1%
#40000
0%
#45000
1%
#50000
0$
0%
#55000
1%
#60000
0%
#65000
1%
#70000
0%
#75000
1%
#80000
0%
#85000
1%
#90000
0%
#95000
1%
#100000
0%
#105000
1%
#110000
0%
#115000
1%
#120000
0%
#125000
1%
#130000
0%
#135000
1%
#140000
0%
#145000
1%
#150000
0%
#155000
1%
#160000
0%
#165000
1%
#170000
0%
#175000
1%
#180000
0%
#185000
1%
#190000
0%
#195000
1%
#200000
0%
1#
#205000
b1 )
1%
#210000
0%
#215000
b11 '
b1 !
b1 (
b1 *
1%
#220000
0%
#225000
b10 '
1%
#230000
0%
#235000
b1 '
1%
#240000
0%
#245000
b0 '
1%
#250000
0%
#255000
b10 )
1%
#260000
0%
#265000
b10 '
b0 !
b0 (
b10 *
1%
#270000
0%
#275000
b1 '
1%
#280000
0%
#285000
b0 '
1%
#290000
0%
#295000
b11 )
1%
#300000
0%
0#
#305000
b10 "
b10 &
b11 *
1%
#310000
0%
#315000
b100 )
1%
#320000
0%
#325000
b11 '
b1 "
b1 &
b100 *
1%
#330000
0%
#335000
b10 '
1%
#340000
0%
#345000
b1 '
1%
#350000
0%
#355000
b0 '
1%
#360000
0%
#365000
b0 )
1%
#370000
0%
#375000
b11 '
b0 "
b0 &
b10 !
b10 (
b0 *
1%
#380000
0%
#385000
b10 '
1%
#390000
0%
#395000
b1 '
1%
#400000
0%
#405000
b0 '
1%
#410000
0%
#415000
1%
#420000
0%
#425000
1%
#430000
0%
#435000
1%
#440000
0%
#445000
1%
#450000
0%
#455000
1%
#460000
0%
#465000
1%
#470000
0%
#475000
1%
#480000
0%
#485000
1%
#490000
0%
#495000
1%
#500000
0%
1#
#505000
b1 )
1%
#510000
0%
#515000
b11 '
b1 !
b1 (
b1 *
1%
#520000
0%
#525000
b10 '
1%
#530000
0%
#535000
b1 '
1%
#540000
0%
#545000
b0 '
1%
#550000
0%
#555000
b10 )
1%
#560000
0%
#565000
b10 '
b0 !
b0 (
b10 *
1%
#570000
0%
#575000
b1 '
1%
#580000
0%
#585000
b0 '
1%
#590000
0%
#595000
b11 )
1%
#600000
0%
0#
#605000
b10 "
b10 &
b11 *
1%
#610000
0%
#615000
b100 )
1%
#620000
0%
#625000
b11 '
b1 "
b1 &
b100 *
1%
#630000
0%
#635000
b10 '
1%
#640000
0%
#645000
b1 '
1%
#650000
0%
#655000
b0 '
1%
#660000
0%
#665000
b0 )
1%
#670000
0%
#675000
b11 '
b0 "
b0 &
b10 !
b10 (
b0 *
1%
#680000
0%
#685000
b10 '
1%
#690000
0%
#695000
b1 '
1%
#700000
0%
#705000
b0 '
1%
#710000
0%
#715000
1%
#720000
0%
#725000
1%
#730000
0%
#735000
1%
#740000
0%
#745000
1%
#750000
0%
#755000
1%
#760000
0%
#765000
1%
#770000
0%
#775000
1%
#780000
0%
#785000
1%
#790000
0%
#795000
1%
#800000
0%
1#
#805000
b1 )
1%
#810000
0%
#815000
b11 '
b1 !
b1 (
b1 *
1%
#820000
0%
#825000
b10 '
1%
#830000
0%
#835000
b1 '
1%
#840000
0%
#845000
b0 '
1%
#850000
0%
#855000
b10 )
1%
#860000
0%
#865000
b10 '
b0 !
b0 (
b10 *
1%
#870000
0%
#875000
b1 '
1%
#880000
0%
#885000
b0 '
1%
#890000
0%
#895000
b11 )
1%
#900000
0%
0#
#905000
b10 "
b10 &
b11 *
1%
#910000
0%
#915000
b100 )
1%
#920000
0%
#925000
b11 '
b1 "
b1 &
b100 *
1%
#930000
0%
#935000
b10 '
1%
#940000
0%
#945000
b1 '
1%
#950000
0%
#955000
b0 '
1%
#960000
0%
#965000
b0 )
1%
#970000
0%
#975000
b11 '
b0 "
b0 &
b10 !
b10 (
b0 *
1%
#980000
0%
#985000
b10 '
1%
#990000
0%
#995000
b1 '
1%
